
{
    "id": 9951,
    "name": "Delucemite Dwelle",
    "author": "Avern",
    "creators": ["Avern, Ebonium"],
    "verifier": "Avern",
    "verification": "https://youtu.be/WgtZWE5xK-s",
    "percentToQualify": "100",
    "password": "Free To Copy",
    "records": [
         {
            "user":"2n04",
            "link":"https://www.youtube.com/watch?v=gQl6M4B9iT4",
            "percent":100,
            "hz":240
         },
         {
            "user":"jrpresley08",
            "link":"https://www.youtube.com/watch?v=gzo8kdcYiUo",
            "percent":100,
            "hz":120
         }
    ]
}
