{
    "id": 5689,
    "name": "o8",
    "author": "Space34",
    "creators": ["Space34"],
    "verifier": "TurboFlash",
    "verification": "https://youtu.be/ea_aO43Ak-s?si=UHF9O99ERnfzGPmu",
    "percentToQualify": "100",
    "password": "Not Copyable",
    "records": [
        {
            "user":"Minotaur256",
            "link":"https://www.youtube.com/watch?v=vlJ5ENRKRQU",
            "percent":100,
            "hz":240
         },
         {
            "user":"IL0vePurple",
            "link":"https://www.youtube.com/watch?v=V9HBho8MyyY",
            "percent":100,
            "hz":240
         }
    ]
}