{
    "id": 7862,
    "name": "Windows Stole Teams",
    "author": "Surgeon",
    "creators": ["Surgeon"],
    "verifier": "games",
    "verification": "https://www.youtube.com/watch?v=uoxrjaml-6c",
    "percentToQualify": 100,
    "password": "Free Copy",
    "records": [
         {
            "user":"Vergit",
            "link":"https://youtu.be/sfV3WvPpw-I",
            "percent":100,
            "hz":240
         },
         {
            "user":"Macaroni & Games",
            "link":"https://www.youtube.com/watch?v=hZzjngjz8ME",
            "percent":100,
            "hz":165
         },
         {
            "user":"DamoonX",
            "link":"https://youtu.be/J5MokbUz4y8",
            "percent":100,
            "hz":144
         },
         {
            "user":"Carrot",
            "link":"https://www.youtube.com/watch?v=Fiqy8nLlEN4",
            "percent":100,
            "hz":144
         }
    ]
}
